alation_ai_agent_sdk-0.12.0.dist-info/METADATA
alation_ai_agent_sdk-0.12.0.dist-info/WHEEL
alation_ai_agent_sdk-0.12.0.dist-info/entry_points.txt
alation_ai_agent_sdk-0.12.0.dist-info/licenses/LICENSE
alation_ai_agent_sdk/__init__.py
alation_ai_agent_sdk/api.py
alation_ai_agent_sdk/data_dict.py
alation_ai_agent_sdk/data_product.py
alation_ai_agent_sdk/errors.py
alation_ai_agent_sdk/event.py
alation_ai_agent_sdk/fields.py
alation_ai_agent_sdk/lineage.py
alation_ai_agent_sdk/lineage_filtering.py
alation_ai_agent_sdk/sdk.py
alation_ai_agent_sdk/tools.py
alation_ai_agent_sdk/types.py
alation_ai_agent_sdk/utils.py
alation_ai_agent_sdk-0.12.0.dist-info/RECORD
