Metadata-Version: 2.1
Name: alation-ai-agent-sdk
Version: 0.12.0
Summary: Alation Agent SDK
Author-Email: "Jagannath (Jags) Saragadam" <jags.saragadam@alation.com>, Lucy Eun <lucy.eun@alation.com>, Ashwin Kumar Muruganandam <ashwin-kumar.muruganandam@alation.com>, Adam Talmadge <adam.talmadge@alation.com>
Maintainer-Email: "Jagannath (Jags) Saragadam" <jags.saragadam@alation.com>, Lucy Eun <lucy.eun@alation.com>, Ashwin Kumar Muruganandam <ashwin-kumar.muruganandam@alation.com>, Adam Talmadge <adam.talmadge@alation.com>
License:                                  Apache License
Project-URL: Homepage, https://github.com/Alation/alation-ai-agent-sdk/tree/main/python/core-sdk
Project-URL: Issues, https://github.com/Alation/alation-ai-agent-sdk/issues
Project-URL: Documentation, https://github.com/Alation/alation-ai-agent-sdk/blob/main/python/core-sdk/README.md
Requires-Python: >=3.10
Requires-Dist: requests~=2.32.0
Requires-Dist: typing_extensions~=4.14.1
